{"itemID": "19469", "chucdanh1": "Chánh án", "vbcancu1": "19482", "ngaycohieuluc": "27/05/2004", "phamvi": "Toàn quốc", "sokihieu": "01/2004/NQ-HĐTP", "linhvuc": "", "loaivanban": "Nghị quyết", "nganh": "Tư pháp", "coquanbanhanh1": "Hội đồng Thẩm phán Toà án nhân dân tối cao", "nguoiki1": "Nguyễn Văn Hiện", "nguonthuthap": "Công báo số 9 năm 2004", "vbcancu2": "22506", "ngaycongbao": "12/05/2004", "ngaybanhanh": "28/04/2004", "tinhtranghieuluc": "Tình trạng hiệu lực:  Hết hiệu lực toàn bộ", "type": "Hướng dẫn áp dụng một số quy định của Bộ Luật Dân sự về bồi thường thiệt hại ngoài hợp đồng", "thongtinapdung": "**Thông tin áp dụng**\n\n"}