{"itemID": "15694", "chucdanh1": "Chủ tịch", "vbcancu1": "22840", "vbcancu3": "9028", "ngaycohieuluc": "13/03/2005", "phamvi": "Toàn quốc", "sokihieu": "746/2005/NQ-UBTVQH11", "vbdanchieu1": "8532", "linhvuc": "", "loaivanban": "Nghị quyết", "nganh": "", "coquanbanhanh1": "Uỷ ban Thường vụ Quốc hội", "nguoiki1": "Nguyễn Văn An", "nguonthuthap": "Công báo số 19 - 02/2005;", "vbcancu2": "22313", "ngaycongbao": "26/02/2005", "ngaybanhanh": "28/01/2005", "tinhtranghieuluc": "Tình trạng hiệu lực:  Còn hiệu lực", "type": "Về việc giải thích điểm c khoản 2 Điều 241 của Luật Thương mại", "thongtinapdung": "**Thông tin áp dụng**\n\n"}