{"itemID": "1334", "chucdanh1": "", "ngaycohieuluc": "11/11/1962", "phamvi": "Toàn quốc", "sokihieu": "Không số", "linhvuc": "", "loaivanban": "Nghị quyết", "nganh": "", "coquanbanhanh1": "Quốc hội", "nguoiki1": "Xuân Thủy", "nguonthuthap": "Công báo điện tử;", "ngaycongbao": "...", "ngaybanhanh": "27/10/1962", "tinhtranghieuluc": "Tình trạng hiệu lực:  Ngưng hiệu lực", "type": "Về việc hợp nhất thành phố Hải Phòng và tỉnh Kiến An, hợp nhất tỉnh Bắc Ninh và tỉnh Bắc Giang", "thongtinapdung": "**Thông tin áp dụng**\n\n"}