{"itemID": "19414", "chucdanh1": "Chủ tịch Quốc hội", "vbcancu1": "22313", "vbduochuongdan1": "22313", "ngaycohieuluc": "01/07/2004", "phamvi": "Toàn quốc", "sokihieu": "16/2003/QH11", "linhvuc": "", "loaivanban": "Luật", "nganh": "", "coquanbanhanh1": "Quốc hội", "nguoiki1": "Nguyễn Văn An", "nguonthuthap": "Công báo số 2, năm 2004", "ngaycongbao": "02/01/2004", "ngaybanhanh": "26/11/2003", "tinhtranghieuluc": "Tình trạng hiệu lực:  Hết hiệu lực toàn bộ", "type": "Xây dựng", "thongtinapdung": "**Thông tin áp dụng**\n\n"}