{"itemID": "2064", "chucdanh1": "Chủ tịch Quốc hội", "vbcancu1": "1534", "vbduochuongdan1": "1534", "ngaycohieuluc": "01/10/1990", "phamvi": "Toàn quốc", "sokihieu": "270B-NQ/HĐNN8", "vbdanchieu1": "3274", "linhvuc": "", "loaivanban": "Luật", "nganh": "Tài chính", "coquanbanhanh1": "Quốc hội", "nguoiki1": "Lê Quang Đạo", "nguonthuthap": "Công báo số 18", "ngaycongbao": "30/09/1990", "ngaybanhanh": "30/06/1990", "tinhtranghieuluc": "Tình trạng hiệu lực:  Hết hiệu lực toàn bộ", "type": "Thuế Doanh thu", "thongtinapdung": "**Thông tin áp dụng**\n\n"}