{"itemID": "19176", "chucdanh1": "Thủ tướng", "vbcancu1": "17815", "vbcancu3": "22843", "ngaycohieuluc": "23/10/2004", "phamvi": "Toàn quốc", "sokihieu": "171/2004/NĐ-CP", "linhvuc": "Tổ chức- Biên chế", "loaivanban": "Nghị định", "nganh": "Nội vụ", "coquanbanhanh1": "Chính phủ", "nguoiki1": "Phan Văn Khải", "nguonthuthap": "Công báo số 6 năm 2004", "vbcancu2": "20068", "ngaycongbao": "08/10/2004", "ngaybanhanh": "29/09/2004", "tinhtranghieuluc": "Tình trạng hiệu lực:  Hết hiệu lực toàn bộ", "type": "Quy định tổ chức các cơ quan chuyên môn thuộc ủy ban nhân dân tỉnh, thành phố trực thuộc Trung ương", "thongtinapdung": "**Thông tin áp dụng**\n\n"}