{"vbduochuongdan1": "27624", "vbduochuongdan2": "16726", "ngaycohieuluc": "25/09/2013", "nguonthuthap": "Công báo số 485+486, năm 2013", "vbbibomotphan1": "13178", "vbcancu2": "16726", "vbcancu3": "22843", "vbcancu1": "27624", "sokihieu": "89/2013/NĐ-CP", "tinhtranghieuluc": "Tình trạng hiệu lực:  Còn hiệu lực", "nguoiki1": "Nguyễn Tấn Dũng", "vbbibomotphan2": "20585", "nganh": "", "type": "Quy định chi tiết thi hành một số điều của Luật Giá về thẩm định giá", "thongtinapdung": "**Thông tin áp dụng**\n\n", "itemID": "31156", "coquanbanhanh1": "Chính phủ", "phamvi": "Toàn quốc", "chucdanh1": "Thủ tướng", "linhvuc": "", "loaivanban": "Nghị định", "ngaycongbao": "18/08/2013", "ngaybanhanh": "06/08/2013"}