{"itemID": "2558", "chucdanh1": "Chủ tịch Quốc hội", "vbcancu1": "1534", "vbduochuongdan1": "1534", "ngaycohieuluc": "15/07/1988", "phamvi": "Toàn quốc", "sokihieu": "Không số", "linhvuc": "Hộ tịch, quốc tịch, chứng thực", "loaivanban": "Luật", "nganh": "Tư pháp", "coquanbanhanh1": "Quốc hội", "nguoiki1": "Lê Quang Đạo", "nguonthuthap": "Công báo số 17", "ngaycongbao": "15/09/1988", "ngaybanhanh": "28/06/1988", "tinhtranghieuluc": "Tình trạng hiệu lực:  Hết hiệu lực toàn bộ", "type": "Quốc tịch Việt Nam", "thongtinapdung": "**Thông tin áp dụng**\n\n"}