{"vbduochuongdan4": "11234", "vbduochuongdan1": "12807", "vbduochuongdan2": "14166", "ngaycohieuluc": "21/06/2012", "nguonthuthap": "Công báo số 477+478, năm 2012", "vbcancu2": "12806", "vbcancu3": "12807", "vbcancu1": "12898", "vbcancu6": "22840", "vbcancu7": "11234", "vbcancu4": "14166", "vbcancu5": "14832", "sokihieu": "29/2012/QH13", "vbduochuongdan3": "14832", "tinhtranghieuluc": "Tình trạng hiệu lực:  Còn hiệu lực", "nguoiki1": "Nguyễn Sinh Hùng", "nganh": "Tài chính", "type": "Về ban hành một số chính sách thuế nhằm tháo gỡ khó khăn cho tổ chức và cá nhân", "thongtinapdung": "**Thông tin áp dụng**\n\n", "itemID": "27655", "coquanbanhanh1": "Quốc hội", "phamvi": "Toàn quốc", "chucdanh1": "Chủ tịch Quốc hội", "linhvuc": "", "loaivanban": "Nghị quyết", "ngaycongbao": "05/08/2012", "ngaybanhanh": "21/06/2012"}