{"itemID": "17593", "chucdanh1": "Chủ tịch Quốc hội", "vbcancu1": "22313", "vbduochuongdan1": "22313", "ngaycohieuluc": "16/09/2005", "phamvi": "Toàn quốc", "sokihieu": "45/2005/QH11", "linhvuc": "", "loaivanban": "Nghị quyết", "nganh": "", "coquanbanhanh1": "Quốc hội", "nguoiki1": "Nguyễn Văn An", "vbbithaythe1": "2310", "nguonthuthap": "Công báo số 01+02+03", "ngaycongbao": "01/09/2005", "ngaybanhanh": "14/06/2005", "tinhtranghieuluc": "Tình trạng hiệu lực:  Còn hiệu lực", "type": "Về việc thi hành Bộ luật Dân sự", "thongtinapdung": "**Thông tin áp dụng**\n\n"}