{"vbduochuongdan4": "16726", "vbduochuongdan5": "16718", "vbduochuongdan6": "16750", "vbduochuongdan7": "21004", "vbduochuongdan1": "28067", "vbduochuongdan2": "26353", "ngaycohieuluc": "01/03/2014", "nguonthuthap": "Công báo số 27+28, năm 2014", "vbcancu8": "22843", "vbcancu2": "26353", "vbcancu3": "11706", "vbcancu1": "28067", "vbcancu6": "16750", "vbcancu7": "21004", "vbcancu4": "16726", "vbcancu5": "16718", "sokihieu": "216/2013/NĐ-CP", "vbduochuongdan3": "11706", "tinhtranghieuluc": "Tình trạng hiệu lực:  Còn hiệu lực", "nguoiki1": "Nguyễn Tấn Dũng", "nganh": "Kế hoạch và Đầu tư", "type": "Về tổ chức và hoạt động thanh tra ngành Kế hoạch và Đầu tư", "thongtinapdung": "**Thông tin áp dụng**\n\n", "itemID": "32889", "coquanbanhanh1": "Chính phủ", "phamvi": "Toàn quốc", "vbbithaythe1": "16946", "chucdanh1": "Thủ tướng", "linhvuc": "", "loaivanban": "Nghị định", "vbdanchieu2": "26790", "vbdanchieu3": "26353", "vbdanchieu1": "27186", "ngaycongbao": "06/01/2014", "ngaybanhanh": "24/12/2013"}