{"vbduochuongdan1": "28019", "vbduochuongdan2": "15076", "ngaycohieuluc": "28/11/2013", "nguonthuthap": "Công báo số 707+708", "vbcancu2": "15076", "vbcancu3": "22843", "vbcancu1": "28019", "sokihieu": "123/2013/NĐ-CP", "vbduochuongdan3": "22843", "tinhtranghieuluc": "Tình trạng hiệu lực:  Còn hiệu lực", "nguoiki1": "Nguyễn Tấn Dũng", "nganh": "Tư pháp", "type": "Quy định chi tiết một số điều và biện pháp thi hành Luật Luật sư", "thongtinapdung": "**Thông tin áp dụng**\n\n\\- Điều lệ Đoàn luật sư được phê duyệt theo quy định của Luật Luật sư số\n65/2006/QH11 tiếp tục được áp dụng cho đến khi Điều lệ Liên đoàn luật sư Việt\nNam quy định tại Điều 67 của Luật Luật sư được cơ quan có thẩm quyền phê\nduyệt, trừ những nội dung trái với quy định của pháp luật và Điều lệ Liên đoàn\nluật sư Việt Nam. \\- Chương trình khung đào tạo nghề luật sư được ban hành kèm\ntheo Quyết định số 90/2008/QĐ-BTP ngày 21 tháng 01 năm 2008 của Bộ trưởng Bộ\nTư pháp được tiếp tục áp dụng đến khi Chương trình khung mới theo quy định tại\nĐiều 12 của Luật Luật sư được Bộ trưởng Bộ Tư pháp ban hành; những người tập\nsự hành nghề luật sư tham gia khóa đào tạo nghề luật sư theo Chương trình\nkhung đào tạo nghề luật sư 06 tháng phải tập sự hành nghề luật sư 18 tháng.\n\n", "itemID": "32496", "vbbihethieuluc1": "12634", "coquanbanhanh1": "Chính phủ", "phamvi": "Toàn quốc", "vbbithaythe2": "14372", "vbbithaythe1": "12634", "chucdanh1": "Thủ tướng", "linhvuc": "Bổ trợ tư pháp", "loaivanban": "Nghị định", "vbbihethieuluc2": "14372", "vbdanchieu1": "15076", "ngaycongbao": "28/10/2013", "ngaybanhanh": "14/10/2013"}