{"ngaycohieuluc": "01/01/2014", "nguonthuthap": "Công báo số 839+840, năm 2013", "vbcancu2": "27621", "vbcancu3": "11716", "vbcancu1": "28015", "vbcancu6": "7039", "vbcancu7": "2083", "vbcancu4": "16748", "vbcancu5": "22843", "sokihieu": "159/2013/NĐ-CP", "tinhtranghieuluc": "Tình trạng hiệu lực:  Còn hiệu lực", "nguoiki1": "Nguyễn Tấn Dũng", "nganh": "Thông tin và Truyền thông", "type": "Quy định xử phạt vi phạm hành chính trong hoạt động báo chí, xuất bản", "thongtinapdung": "**Thông tin áp dụng**\n\n", "itemID": "32602", "coquanbanhanh1": "Chính phủ", "phamvi": "Toàn quốc", "vbbithaythe1": "26065", "chucdanh1": "Thủ tướng", "linhvuc": "", "loaivanban": "Nghị định", "vbdanchieu1": "27621", "ngaycongbao": "01/12/2013", "ngaybanhanh": "12/11/2013"}