{"vbduochuongdan1": "20957", "vbduochuongdan2": "21622", "ngaycohieuluc": "09/01/2008", "nguonthuthap": "", "vbcancu2": "20957", "vbcancu3": "21461", "vbcancu1": "19661", "vbcancu4": "21622", "sokihieu": "3982/QĐ-BTC", "tinhtranghieuluc": "Tình trạng hiệu lực:  Hết hiệu lực toàn bộ", "nguoiki1": "Trần Văn Tá", "nganh": "Tài chính", "type": "Ban hành Quy chế kiểm tra và xử lý văn bản của Bộ Tài chính", "thongtinapdung": "**Thông tin áp dụng**\n\n", "itemID": "76706", "coquanbanhanh1": "Bộ Tài chính", "phamvi": "Toàn quốc", "chucdanh1": "Thứ trưởng", "linhvuc": "", "loaivanban": "Quyết định", "vbdanchieu2": "18527", "vbdanchieu3": "17023", "vbdanchieu1": "18349", "ngaycongbao": "...", "ngaybanhanh": "25/12/2007"}