{"vbduochuongdan1": "17456", "ngaycohieuluc": "19/06/2010", "nguonthuthap": "Công báo số 238+239, năm 2010", "vbcancu2": "17456", "vbcancu3": "22843", "vbcancu1": "12803", "sokihieu": "01/2010/NQLT-CP-HCCBVN", "tinhtranghieuluc": "Tình trạng hiệu lực:  Còn hiệu lực", "nguoiki2": "Trần Hanh", "nguoiki1": "Nguyễn Tấn Dũng", "nganh": "", "type": "Về việc ban hành Quy chế phối hợp công tác giữa Chính phủ và Trung ương Hội cựu chiến binh Việt Nam", "thongtinapdung": "**Thông tin áp dụng**\n\n", "itemID": "25270", "coquanbanhanh2": "Hội Cựu chiến binh Việt Nam", "coquanbanhanh1": "Chính phủ", "phamvi": "Toàn quốc", "chucdanh2": "Chủ tịch", "chucdanh1": "Thủ tướng", "linhvuc": "", "loaivanban": "Nghị quyết liên tịch", "ngaycongbao": "21/05/2010", "ngaybanhanh": "05/05/2010"}