{"vbduochuongdan1": "25961", "vbduochuongdan2": "10803", "ngaycohieuluc": "15/05/2011", "nguonthuthap": "Công báo số 171+172, năm 2011", "vbcancu2": "22843", "vbcancu3": "10803", "vbcancu1": "25961", "sokihieu": "20/2011/NĐ-CP", "tinhtranghieuluc": "Tình trạng hiệu lực:  Hết hiệu lực một phần", "nguoiki1": "Nguyễn Tấn Dũng", "nganh": "Tài chính", "type": "Quy định chi tiết và hướng dẫn thi hành Nghị quyết số 55/2010/QH12 ngày 24 tháng 11 năm 2010 của Quốc hội về miễn, giảm thuế sử dụng đất nông nghiệp", "thongtinapdung": "**Thông tin áp dụng**\n\n", "itemID": "26225", "coquanbanhanh1": "Chính phủ", "phamvi": "Toàn quốc", "chucdanh1": "Thủ tướng", "linhvuc": "", "loaivanban": "Nghị định", "vbdanchieu4": "19412", "vbdanchieu5": "19419", "vbdanchieu2": "17152", "vbdanchieu3": "18542", "vbdanchieu1": "14044", "ngaycongbao": "05/04/2011", "ngaybanhanh": "23/03/2011"}