{"itemID": "1340", "chucdanh1": "", "vbcancu1": "889", "ngaycohieuluc": "30/08/1962", "phamvi": "Toàn quốc", "sokihieu": "125-NQ/TVQH", "linhvuc": "", "loaivanban": "Nghị quyết", "nganh": "", "coquanbanhanh1": "Uỷ ban Thường vụ Quốc hội", "nguoiki1": "Xuân Thủy", "nguonthuthap": "Hồ sơ 379/LTQG;", "ngaycongbao": "...", "ngaybanhanh": "30/08/1962", "tinhtranghieuluc": "Tình trạng hiệu lực:  Hết hiệu lực toàn bộ", "type": "Về việc đặc xá cho những phạm nhân cải tạo tốt", "thongtinapdung": "**Thông tin áp dụng**\n\n"}