{"itemID": "19393", "chucdanh1": "Chủ tịch", "ngaycohieuluc": "24/06/2004", "phamvi": "Toàn quốc", "sokihieu": "28/2004/QH11", "linhvuc": "", "loaivanban": "Nghị quyết", "nganh": "", "coquanbanhanh1": "Quốc hội", "nguoiki1": "Nguyễn Văn An", "nguonthuthap": "Công báo số 29 - 30/2004;", "ngaycongbao": "18/07/2004", "ngaybanhanh": "15/06/2004", "tinhtranghieuluc": "Tình trạng hiệu lực:  Còn hiệu lực", "type": "Về việc phê chuẩn \"Hiệp định giữa nước Cộng hoà xã hội chủ nghĩa Việt Nam và nước Cộng hoà nhân dân Trung Hoa về phân định lãnh hải, vùng đặc quyền kinh tế và thềm lục địa của hai nước trong vịnh Bắc Bộ\"", "thongtinapdung": "**Thông tin áp dụng**\n\n"}