{"vbduochuongdan1": "12352", "vbduochuongdan2": "22843", "ngaycohieuluc": "01/06/2013", "nguonthuthap": "", "vbcancu2": "22843", "vbcancu1": "12352", "sokihieu": "29/2013/NĐ-CP", "tinhtranghieuluc": "Tình trạng hiệu lực:  Còn hiệu lực", "nguoiki1": "Nguyễn Tấn Dũng", "nganh": "Nội vụ", "type": "Sửa đổi, bổ sung một số điều của Nghị định số 92/2009/NĐ-CP ngày 22 tháng 10 năm 2009 của Chính phủ về chức danh, số lượng, một số chế độ, chính sách đối với cán bộ, công chức ở xã, phường, thị trấn và những người hoạt động không chuyên trách ở cấp xã", "thongtinapdung": "**Thông tin áp dụng**\n\n", "itemID": "113275", "vbsuadoibosung1": "113253", "coquanbanhanh1": "Chính phủ", "phamvi": "Toàn quốc", "chucdanh1": "Thủ tướng Chính phủ", "linhvuc": "Chính quyền địa phương", "loaivanban": "Nghị định", "vbdanchieu4": "16319", "vbdanchieu5": "7998", "vbdanchieu2": "23668", "vbdanchieu3": "12085", "vbdanchieu1": "25239", "ngaycongbao": "...", "ngaybanhanh": "08/04/2013"}