{"vbduochuongdan1": "12674", "vbduochuongdan2": "18131", "ngaycohieuluc": "01/09/2011", "nguonthuthap": "Công báo 393+394, năm 2011", "vbcancu2": "18131", "vbcancu3": "22291", "vbcancu1": "12674", "vbcancu4": "22843", "sokihieu": "48/2011/NĐ-CP", "vbduochuongdan3": "22291", "tinhtranghieuluc": "Tình trạng hiệu lực:  Hết hiệu lực toàn bộ", "nguoiki1": "Nguyễn Tấn Dũng", "nganh": "Giao thông Vận tải", "type": "Quy định xử phạt vi phạm hành chính trong lĩnh vực hàng hải", "thongtinapdung": "**Thông tin áp dụng**\n\n", "itemID": "26526", "coquanbanhanh1": "Chính phủ", "phamvi": "Toàn quốc", "vbbithaythe1": "15913", "chucdanh1": "Thủ tướng Chính phủ", "linhvuc": "Hàng hải", "loaivanban": "Nghị định", "ngaycongbao": "03/07/2011", "ngaybanhanh": "21/06/2011"}