{"itemID": "12258", "chucdanh1": "Thủ tướng", "vbcancu1": "22843", "ngaycohieuluc": "03/05/2008", "phamvi": "Toàn quốc", "sokihieu": "42/2008/NĐ-CP", "linhvuc": "", "loaivanban": "Nghị định", "nganh": "Nội vụ", "coquanbanhanh1": "Chính phủ", "nguoiki1": "Nguyễn Tấn Dũng", "nguonthuthap": "Công báo số 235 + 236, năm 2008", "ngaycongbao": "18/04/2008", "ngaybanhanh": "08/04/2008", "tinhtranghieuluc": "Tình trạng hiệu lực:  Còn hiệu lực", "type": "Về việc điều chỉnh địa giới hành chính xã, thành lập xã thuộchuyện Quế Sơn, huyện Phước Sơn; điều chỉnh địa giới hành chínhhuyện Quế Sơn để thành lập huyện Nông Sơn, tỉnh Quảng Nam", "thongtinapdung": "**Thông tin áp dụng**\n\n"}