{"itemID": "113072", "chucdanh1": "Thủ tướng", "ngaycohieuluc": "01/07/2016", "phamvi": "Toàn quốc", "sokihieu": "103/2016/NĐ-CP", "linhvuc": "Y tế dự phòng", "loaivanban": "Nghị định", "nganh": "Y  tế", "coquanbanhanh1": "Chính phủ", "nguoiki1": "Nguyễn Xuân Phúc", "nguonthuthap": "", "ngaycongbao": "...", "ngaybanhanh": "01/07/2016", "tinhtranghieuluc": "Tình trạng hiệu lực:  Còn hiệu lực", "type": "Quy định về bảo đảm an toàn sinh học tại phòng xét nghiệm", "thongtinapdung": "**Thông tin áp dụng**\n\n"}