{"itemID": "18319", "chucdanh1": "Thủ tướng", "vbcancu1": "22843", "ngaycohieuluc": "10/11/2004", "phamvi": "Toàn quốc", "sokihieu": "179/2004/NĐ-CP", "linhvuc": "", "loaivanban": "Nghị định", "nganh": "Khoa học và công nghệ", "coquanbanhanh1": "Chính phủ", "nguoiki1": "Phan Văn Khải", "nguonthuthap": "Công báo số 19, năm 2004", "vbcancu2": "6528", "ngaycongbao": "26/10/2004", "ngaybanhanh": "21/10/2004", "tinhtranghieuluc": "Tình trạng hiệu lực:  Hết hiệu lực toàn bộ", "type": "Quy định quản lý nhà nước về chất lượng sản phẩm, hàng hoá", "thongtinapdung": "**Thông tin áp dụng**\n\n"}