{"ngaycohieuluc": "09/01/2006", "nguonthuthap": "Công báo số 29 & 30 - 12/2005;", "vbcancu2": "22843", "vbcancu3": "23289", "vbcancu1": "22291", "vbcancu4": "9822", "vbcancu5": "2322", "sokihieu": "152/2005/NĐ-CP", "tinhtranghieuluc": "Tình trạng hiệu lực:  Hết hiệu lực toàn bộ", "nguoiki1": "Phan Văn Khải", "nganh": "Giao thông Vận tải", "type": "Quy định về xử lý vi phạm hành chính trong lĩnh vực giao thông đường bộ", "thongtinapdung": "**Thông tin áp dụng**\n\n", "itemID": "16905", "coquanbanhanh1": "Chính phủ", "phamvi": "Toàn quốc", "vbbithaythe2": "21767", "vbbithaythe1": "20465", "chucdanh1": "Thủ tướng", "linhvuc": "Đường bộ", "loaivanban": "Nghị định", "vbdanchieu2": "20956", "vbdanchieu3": "22291", "vbdanchieu1": "18448", "ngaycongbao": "25/12/2005", "ngaybanhanh": "15/12/2005"}