{"itemID": "15092", "chucdanh1": "Thủ tướng", "vbcancu1": "16872", "ngaycohieuluc": "16/11/2006", "phamvi": "Toàn quốc", "sokihieu": "120/2006/NĐ-CP", "vbdanchieu1": "16872", "linhvuc": "", "loaivanban": "Nghị định", "nganh": "Thanh tra", "coquanbanhanh1": "Chính phủ", "nguoiki1": "Nguyễn Tấn Dũng", "nguonthuthap": "Công báo số 1+2, năm 2006", "vbcancu2": "22843", "ngaycongbao": "01/11/2006", "ngaybanhanh": "20/10/2006", "tinhtranghieuluc": "Tình trạng hiệu lực:  Hết hiệu lực toàn bộ", "type": "Quy định chi tiết và hướng dẫn thi hành một số điều của Luật Phòng, chống tham nhũng", "thongtinapdung": "**Thông tin áp dụng**\n\n"}