{"itemID": "2094", "chucdanh1": "Chủ tịch Quốc hội", "vbcancu1": "1534", "ngaycohieuluc": "28/12/1989", "phamvi": "Toàn quốc", "sokihieu": "Không số", "linhvuc": "", "loaivanban": "Nghị quyết", "nganh": "", "coquanbanhanh1": "Quốc hội", "nguoiki1": "Lê Quang Đạo", "nguonthuthap": "Công báo số 1, năm1990", "ngaycongbao": "15/01/1990", "ngaybanhanh": "28/12/1989", "tinhtranghieuluc": "Tình trạng hiệu lực:  Hết hiệu lực toàn bộ", "type": "Về nhiệm vụ phát triển kinh tế - xã hội năm 1990", "thongtinapdung": "**Thông tin áp dụng**\n\n"}