{"itemID": "25238", "chucdanh1": "Thủ tướng", "vbcancu1": "16753", "ngaycohieuluc": "20/07/2010", "phamvi": "Toàn quốc", "sokihieu": "59/2010/NĐ-CP", "vbdanchieu1": "18433", "linhvuc": "", "loaivanban": "Nghị định", "vbsuadoibosung1": "14460", "nganh": "Công an", "coquanbanhanh1": "Chính phủ", "nguoiki1": "Nguyễn Tấn Dũng", "nguonthuthap": "Công báo số 357+358, năm 2010", "vbcancu2": "22843", "ngaycongbao": "17/06/2010", "ngaybanhanh": "02/06/2010", "tinhtranghieuluc": "Tình trạng hiệu lực:  Còn hiệu lực", "type": "Sửa đổi, bổ sung một số điều về chế độ, chính sách đối với sĩ quan, hạ sĩ quan Công an nhân dân nghỉ hưu, hy sinh, từ trần quy định tại Nghị định số 43/2007/NĐ-CP ngày 26 tháng 3 năm 2007 của Chính phủ quy định chi tiết và hướng dẫn thi hành một số điều của Luật Công an nhân dân", "thongtinapdung": "**Thông tin áp dụng**\n\n"}